{
  "$schema": "https://developer.microsoft.com/json-schemas/fabric/item/report/definition/visualContainer/2.10.0/schema.json",
  "name": "8130a0dd23eeaca0650e",
  "position": {
    "x": 845.71428571428578,
    "y": 617.14285714285722,
    "z": 1,
    "height": 12.857142857142858,
    "width": 300,
    "tabOrder": 1
  },
  "visual": {
    "visualType": "textbox",
    "objects": {
      "general": [
        {
          "properties": {
            "paragraphs": [
              {
                "textRuns": [
                  {
                    "value": ""
                  }
                ]
              }
            ]
          }
        }
      ]
    },
    "drillFilterOtherVisuals": true
  }
}